migho_yt/__init__.py
migho_yt-0.0.1.dist-info/LICENCE.txt
migho_yt-0.0.1.dist-info/METADATA
migho_yt-0.0.1.dist-info/WHEEL
migho_yt-0.0.1.dist-info/top_level.txt
migho_yt-0.0.1.dist-info/RECORD
