Metadata-Version: 2.1
Name: migho-yt
Version: 0.0.1
Summary: with This Package can download from YouTube so Fast :/
Home-page: UNKNOWN
Author: Migho Ahmed
Author-email: migho.ahmed@gmail.com
License: MIT
Keywords: Youtube,SoundCloud,migho,instagram,tool,pypi
Platform: UNKNOWN
Classifier: Development Status :: 5 - Production/Stable
Classifier: Intended Audience :: Education
Classifier: Operating System :: Microsoft :: Windows :: Windows 10
Classifier: License :: OSI Approved :: MIT License
Classifier: Programming Language :: Python :: 3
Requires-Dist: requests
Requires-Dist: pytube
